word2number_en/__init__.py
word2number_en/w2n.py
word2number_en-1.0.0.dist-info/LICENSE.txt
word2number_en-1.0.0.dist-info/METADATA
word2number_en-1.0.0.dist-info/WHEEL
word2number_en-1.0.0.dist-info/top_level.txt
word2number_en-1.0.0.dist-info/RECORD
