Metadata-Version: 2.1
Name: word2number-en
Version: 1.0.0
Summary: Convert number words (eg. twenty one) to numeric digits (21)
Home-page: https://github.com/Neuri-ai/w2n_en
Author: Neuri
Author-email: support@neuri.ai
License: The MIT License (MIT)
Keywords: numbers,convert,words,english
Classifier: Intended Audience :: Developers
Classifier: Programming Language :: Python
License-File: LICENSE.txt
